monke/README.txt.py
monke/__init__.py
monke/constants.py
monke/fit.py
monke/functions.py
monke/latex.py
monke/latexgraphic.py
monke/plots.py
monke/readme.py
monke/texfile.py
monke/textable.py
monke2-1.4.14.dist-info/LICENSE
monke2-1.4.14.dist-info/METADATA
monke2-1.4.14.dist-info/WHEEL
monke2-1.4.14.dist-info/top_level.txt
monke2-1.4.14.dist-info/RECORD
