Metadata-Version: 2.1
Name: monke2
Version: 1.4.14
Summary: erstellt Geraden-Fits, physikalische Konstanten etc.
Author: Gabriel Remiszewski
Classifier: Programming Language :: Python :: 3
Classifier: License :: OSI Approved :: MIT License
Classifier: Operating System :: OS Independent
Requires-Python: >=3.10
License-File: LICENSE
